thonnycontrib/plugin_loader.py
thonnycontrib/docs/__init__.py
thonnycontrib/docs/res/failed.png
thonnycontrib/docs/res/failed1.jpg
thonnycontrib/docs/res/l1test_icon.png
thonnycontrib/docs/res/passed.png
thonnycontrib/docs/res/png-clipart-computer-icons-error-checklist-trademark-area.png
thonnycontrib/docs/res/warning.png
thonnycontrib/docstring_generator/DocGenerator.py
thonnycontrib/docstring_generator/DocTemplate.py
thonnycontrib/docstring_generator/__init__.py
thonnycontrib/l1test/ASTParser.py
thonnycontrib/l1test/Evaluator.py
thonnycontrib/l1test/TestReporter.py
thonnycontrib/l1test/TestRunner.py
thonnycontrib/l1test/ThonnyLogsGenerator.py
thonnycontrib/l1test/__init__.py
thonnycontrib/l1test/exceptions.py
thonnycontrib/l1test/myDoctest.py
thonnycontrib/l1test/properties.py
thonnycontrib/l1test/utils.py
thonnycontrib/l1test/classe/EmptyTest.py
thonnycontrib/l1test/classe/ExceptionTest.py
thonnycontrib/l1test/classe/FailedTest.py
thonnycontrib/l1test/classe/PassedTest.py
thonnycontrib/l1test/classe/Test.py
thonnycontrib/l1test/classe/__init__.py
thonnycontrib/tests/__init__.py
thonnycontrib/tests/test_evaluator.py
thonny_tests-2.0.1.dist-info/LICENSE
thonny_tests-2.0.1.dist-info/METADATA
thonny_tests-2.0.1.dist-info/WHEEL
thonny_tests-2.0.1.dist-info/top_level.txt
thonny_tests-2.0.1.dist-info/RECORD
