Metadata-Version: 2.1
Name: thonny-tests
Version: 2.0.1
Summary: A plug-in which adds a test framework
Home-page: https://gitlab.univ-lille.fr/mirabelle.nebut/thonny-tests
Author: Mirabelle MARVIE-NEBUT, Maude PUPIN
License: UNKNOWN
Keywords: IDE education programming tests in documentation
Platform: Windows
Platform: macOS
Platform: Linux
Requires-Python: >=3.7
License-File: LICENSE
Requires-Dist: thonny (>=3.2.1)
